[
  {
    "longitude": 80.3565,
    "latitude": 16.5747,
    "weather_id": 802,
    "weather_main": "Clouds",
    "weather_description": "scattered clouds",
    "weather_icon": "03n",
    "temperature": 28.920000000000016,
    "feels_like": 35.920000000000016,
    "temp_min": 28.920000000000016,
    "temp_max": 28.920000000000016,
    "pressure": 1013,
    "humidity": 88,
    "sea_level": 1013,
    "ground_level": 1007,
    "visibility": 10000,
    "wind_speed": 2.97,
    "wind_degree": 154,
    "wind_gust": 3.48,
    "rain_1h": null,
    "clouds": 43,
    "datetime": "2024-11-02T14:02:32",
    "country": "IN",
    "sunrise": "2024-11-02T00:36:33",
    "sunset": "2024-11-02T12:07:37",
    "timezone": 19800,
    "city_id": 1266209,
    "city_name": "Amaravati"
  },
  {
    "longitude": 93.6167,
    "latitude": 27.1,
    "weather_id": 800,
    "weather_main": "Clear",
    "weather_description": "clear sky",
    "weather_icon": "01n",
    "temperature": 19.75,
    "feels_like": 20.129999999999995,
    "temp_min": 19.75,
    "temp_max": 19.75,
    "pressure": 1016,
    "humidity": 90,
    "sea_level": 1016,
    "ground_level": 949,
    "visibility": 10000,
    "wind_speed": 1.99,
    "wind_degree": 336,
    "wind_gust": 1.25,
    "rain_1h": null,
    "clouds": 0,
    "datetime": "2024-11-02T14:03:15",
    "country": "IN",
    "sunrise": "2024-11-01T23:56:14",
    "sunset": "2024-11-02T11:01:51",
    "timezone": 19800,
    "city_id": 1269655,
    "city_name": "Itanagar"
  },
  {
    "longitude": 91.7889,
    "latitude": 26.1425,
    "weather_id": 800,
    "weather_main": "Clear",
    "weather_description": "clear sky",
    "weather_icon": "01n",
    "temperature": 25.970000000000027,
    "feels_like": 25.970000000000027,
    "temp_min": 25.970000000000027,
    "temp_max": 25.970000000000027,
    "pressure": 1014,
    "humidity": 86,
    "sea_level": 1014,
    "ground_level": 993,
    "visibility": 10000,
    "wind_speed": 1.02,
    "wind_degree": 157,
    "wind_gust": 0.84,
    "rain_1h": null,
    "clouds": 0,
    "datetime": "2024-11-02T14:03:16",
    "country": "IN",
    "sunrise": "2024-11-02T00:02:18",
    "sunset": "2024-11-02T11:10:24",
    "timezone": 19800,
    "city_id": 1272508,
    "city_name": "Dispur"
  },
  {
    "longitude": 85.1167,
    "latitude": 25.6,
    "weather_id": 701,
    "weather_main": "Mist",
    "weather_description": "mist",
    "weather_icon": "50n",
    "temperature": 27.960000000000036,
    "feels_like": 33.450000000000045,
    "temp_min": 27.960000000000036,
    "temp_max": 27.960000000000036,
    "pressure": 1013,
    "humidity": 89,
    "sea_level": 1013,
    "ground_level": 1007,
    "visibility": 1600,
    "wind_speed": 0,
    "wind_degree": 0,
    "wind_gust": null,
    "rain_1h": null,
    "clouds": 0,
    "datetime": "2024-11-02T14:02:46",
    "country": "IN",
    "sunrise": "2024-11-02T00:28:19",
    "sunset": "2024-11-02T11:37:47",
    "timezone": 19800,
    "city_id": 1260086,
    "city_name": "Patna"
  },
  {
    "longitude": 81.6333,
    "latitude": 21.2333,
    "weather_id": 721,
    "weather_main": "Haze",
    "weather_description": "haze",
    "weather_icon": "50n",
    "temperature": 26.08000000000004,
    "feels_like": 26.08000000000004,
    "temp_min": 26.08000000000004,
    "temp_max": 26.08000000000004,
    "pressure": 1014,
    "humidity": 57,
    "sea_level": 1014,
    "ground_level": 980,
    "visibility": 3000,
    "wind_speed": 1.03,
    "wind_degree": 160,
    "wind_gust": null,
    "rain_1h": null,
    "clouds": 40,
    "datetime": "2024-11-02T14:03:17",
    "country": "IN",
    "sunrise": "2024-11-02T00:36:52",
    "sunset": "2024-11-02T11:57:06",
    "timezone": 19800,
    "city_id": 1258980,
    "city_name": "Raipur"
  },
  {
    "longitude": 73.8333,
    "latitude": 15.4833,
    "weather_id": 211,
    "weather_main": "Thunderstorm",
    "weather_description": "thunderstorm",
    "weather_icon": "11n",
    "temperature": 28.0,
    "feels_like": 31.210000000000036,
    "temp_min": 28.0,
    "temp_max": 28.0,
    "pressure": 1011,
    "humidity": 74,
    "sea_level": 1011,
    "ground_level": 1011,
    "visibility": 5000,
    "wind_speed": 2.57,
    "wind_degree": 40,
    "wind_gust": null,
    "rain_1h": null,
    "clouds": 75,
    "datetime": "2024-11-02T14:03:17",
    "country": "IN",
    "sunrise": "2024-11-02T01:01:25",
    "sunset": "2024-11-02T12:34:57",
    "timezone": 19800,
    "city_id": 1260607,
    "city_name": "Panjim"
  },
  {
    "longitude": 72.6833,
    "latitude": 23.2167,
    "weather_id": 711,
    "weather_main": "Smoke",
    "weather_description": "smoke",
    "weather_icon": "50n",
    "temperature": 30.99000000000001,
    "feels_like": 29.629999999999995,
    "temp_min": 30.99000000000001,
    "temp_max": 30.99000000000001,
    "pressure": 1013,
    "humidity": 29,
    "sea_level": 1013,
    "ground_level": 1004,
    "visibility": 5000,
    "wind_speed": 1.54,
    "wind_degree": 320,
    "wind_gust": null,
    "rain_1h": null,
    "clouds": 0,
    "datetime": "2024-11-02T14:01:08",
    "country": "IN",
    "sunrise": "2024-11-02T01:15:05",
    "sunset": "2024-11-02T12:30:29",
    "timezone": 19800,
    "city_id": 1271715,
    "city_name": "Gandhinagar"
  },
  {
    "longitude": 76.7933,
    "latitude": 30.7343,
    "weather_id": 800,
    "weather_main": "Clear",
    "weather_description": "clear sky",
    "weather_icon": "01n",
    "temperature": 22.610000000000014,
    "feels_like": 21.660000000000025,
    "temp_min": 22.610000000000014,
    "temp_max": 22.610000000000014,
    "pressure": 1014,
    "humidity": 28,
    "sea_level": 1014,
    "ground_level": 973,
    "visibility": 10000,
    "wind_speed": 2.76,
    "wind_degree": 87,
    "wind_gust": 2.62,
    "rain_1h": null,
    "clouds": 0,
    "datetime": "2024-11-02T14:02:10",
    "country": "IN",
    "sunrise": "2024-11-02T01:08:29",
    "sunset": "2024-11-02T12:04:11",
    "timezone": 19800,
    "city_id": 1274746,
    "city_name": "Chandigarh"
  },
  {
    "longitude": 77.1667,
    "latitude": 31.1,
    "weather_id": 800,
    "weather_main": "Clear",
    "weather_description": "clear sky",
    "weather_icon": "01n",
    "temperature": 9.600000000000023,
    "feels_like": 8.689999999999998,
    "temp_min": 9.600000000000023,
    "temp_max": 9.600000000000023,
    "pressure": 1018,
    "humidity": 49,
    "sea_level": 1018,
    "ground_level": 854,
    "visibility": 10000,
    "wind_speed": 2.04,
    "wind_degree": 80,
    "wind_gust": 1.72,
    "rain_1h": null,
    "clouds": 0,
    "datetime": "2024-11-02T14:03:19",
    "country": "IN",
    "sunrise": "2024-11-02T01:07:30",
    "sunset": "2024-11-02T12:02:11",
    "timezone": 19800,
    "city_id": 1256237,
    "city_name": "Shimla"
  },
  {
    "longitude": 85.3333,
    "latitude": 23.35,
    "weather_id": 721,
    "weather_main": "Haze",
    "weather_description": "haze",
    "weather_icon": "50n",
    "temperature": 22.060000000000002,
    "feels_like": 21.710000000000036,
    "temp_min": 22.060000000000002,
    "temp_max": 22.060000000000002,
    "pressure": 1015,
    "humidity": 53,
    "sea_level": 1015,
    "ground_level": 941,
    "visibility": 3500,
    "wind_speed": 4.63,
    "wind_degree": 340,
    "wind_gust": null,
    "rain_1h": null,
    "clouds": 0,
    "datetime": "2024-11-02T14:01:22",
    "country": "IN",
    "sunrise": "2024-11-02T00:24:38",
    "sunset": "2024-11-02T11:39:44",
    "timezone": 19800,
    "city_id": 1258526,
    "city_name": "Ranchi"
  },
  {
    "longitude": 77.6033,
    "latitude": 12.9762,
    "weather_id": 802,
    "weather_main": "Clouds",
    "weather_description": "scattered clouds",
    "weather_icon": "03n",
    "temperature": 26.80000000000001,
    "feels_like": 28.82000000000005,
    "temp_min": 25.900000000000034,
    "temp_max": 26.80000000000001,
    "pressure": 1014,
    "humidity": 74,
    "sea_level": 1014,
    "ground_level": 916,
    "visibility": 6000,
    "wind_speed": 3.09,
    "wind_degree": 90,
    "wind_gust": null,
    "rain_1h": null,
    "clouds": 40,
    "datetime": "2024-11-02T13:56:50",
    "country": "IN",
    "sunrise": "2024-11-02T00:43:33",
    "sunset": "2024-11-02T12:22:39",
    "timezone": 19800,
    "city_id": 1277333,
    "city_name": "Bengaluru"
  },
  {
    "longitude": 76.9167,
    "latitude": 8.4833,
    "weather_id": 211,
    "weather_main": "Thunderstorm",
    "weather_description": "thunderstorm",
    "weather_icon": "11n",
    "temperature": 23.99000000000001,
    "feels_like": 24.74000000000001,
    "temp_min": 23.99000000000001,
    "temp_max": 23.99000000000001,
    "pressure": 1012,
    "humidity": 88,
    "sea_level": 1012,
    "ground_level": 1011,
    "visibility": 2500,
    "wind_speed": 1.54,
    "wind_degree": 40,
    "wind_gust": null,
    "rain_1h": null,
    "clouds": 75,
    "datetime": "2024-11-02T14:02:37",
    "country": "IN",
    "sunrise": "2024-11-02T00:41:25",
    "sunset": "2024-11-02T12:30:17",
    "timezone": 19800,
    "city_id": 1254163,
    "city_name": "Trivandrum"
  },
  {
    "longitude": 77.4,
    "latitude": 23.2667,
    "weather_id": 800,
    "weather_main": "Clear",
    "weather_description": "clear sky",
    "weather_icon": "01n",
    "temperature": 25.700000000000045,
    "feels_like": 25.29000000000002,
    "temp_min": 25.700000000000045,
    "temp_max": 25.700000000000045,
    "pressure": 1014,
    "humidity": 37,
    "sea_level": 1014,
    "ground_level": 957,
    "visibility": 10000,
    "wind_speed": 0.78,
    "wind_degree": 1,
    "wind_gust": 0.99,
    "rain_1h": null,
    "clouds": 0,
    "datetime": "2024-11-02T13:57:16",
    "country": "IN",
    "sunrise": "2024-11-02T00:56:16",
    "sunset": "2024-11-02T12:11:33",
    "timezone": 19800,
    "city_id": 1275841,
    "city_name": "Bhopal"
  },
  {
    "longitude": 72.8479,
    "latitude": 19.0144,
    "weather_id": 711,
    "weather_main": "Smoke",
    "weather_description": "smoke",
    "weather_icon": "50n",
    "temperature": 31.99000000000001,
    "feels_like": 35.620000000000005,
    "temp_min": 31.99000000000001,
    "temp_max": 31.99000000000001,
    "pressure": 1011,
    "humidity": 55,
    "sea_level": 1011,
    "ground_level": 1011,
    "visibility": 3000,
    "wind_speed": 2.57,
    "wind_degree": 350,
    "wind_gust": null,
    "rain_1h": null,
    "clouds": 20,
    "datetime": "2024-11-02T14:00:17",
    "country": "IN",
    "sunrise": "2024-11-02T01:09:24",
    "sunset": "2024-11-02T12:34:51",
    "timezone": 19800,
    "city_id": 1275339,
    "city_name": "Mumbai"
  },
  {
    "longitude": 93.95,
    "latitude": 24.8167,
    "weather_id": 800,
    "weather_main": "Clear",
    "weather_description": "clear sky",
    "weather_icon": "01n",
    "temperature": 18.32000000000005,
    "feels_like": 18.400000000000034,
    "temp_min": 18.32000000000005,
    "temp_max": 18.32000000000005,
    "pressure": 1016,
    "humidity": 84,
    "sea_level": 1016,
    "ground_level": 913,
    "visibility": 10000,
    "wind_speed": 1.27,
    "wind_degree": 20,
    "wind_gust": 1.09,
    "rain_1h": null,
    "clouds": 0,
    "datetime": "2024-11-02T14:03:21",
    "country": "IN",
    "sunrise": "2024-11-01T23:51:58",
    "sunset": "2024-11-02T11:03:27",
    "timezone": 19800,
    "city_id": 1269771,
    "city_name": "Imphal"
  },
  {
    "longitude": 91.8831,
    "latitude": 25.5689,
    "weather_id": 800,
    "weather_main": "Clear",
    "weather_description": "clear sky",
    "weather_icon": "01n",
    "temperature": 15.07000000000005,
    "feels_like": 15.140000000000043,
    "temp_min": 15.07000000000005,
    "temp_max": 15.07000000000005,
    "pressure": 1018,
    "humidity": 96,
    "sea_level": 1018,
    "ground_level": 857,
    "visibility": 10000,
    "wind_speed": 0.3,
    "wind_degree": 42,
    "wind_gust": 1.07,
    "rain_1h": null,
    "clouds": 1,
    "datetime": "2024-11-02T14:03:22",
    "country": "IN",
    "sunrise": "2024-11-02T00:01:12",
    "sunset": "2024-11-02T11:10:46",
    "timezone": 19800,
    "city_id": 1256523,
    "city_name": "Shillong"
  },
  {
    "longitude": 92.7167,
    "latitude": 23.7333,
    "weather_id": 800,
    "weather_main": "Clear",
    "weather_description": "clear sky",
    "weather_icon": "01n",
    "temperature": 18.939999999999998,
    "feels_like": 19.189999999999998,
    "temp_min": 18.939999999999998,
    "temp_max": 18.939999999999998,
    "pressure": 1014,
    "humidity": 88,
    "sea_level": 1014,
    "ground_level": 949,
    "visibility": 10000,
    "wind_speed": 0.7,
    "wind_degree": 97,
    "wind_gust": 0.61,
    "rain_1h": null,
    "clouds": 5,
    "datetime": "2024-11-02T14:01:01",
    "country": "IN",
    "sunrise": "2024-11-01T23:55:33",
    "sunset": "2024-11-02T11:09:44",
    "timezone": 19800,
    "city_id": 1279186,
    "city_name": "Aizawl"
  },
  {
    "longitude": 94.1167,
    "latitude": 25.6667,
    "weather_id": 800,
    "weather_main": "Clear",
    "weather_description": "clear sky",
    "weather_icon": "01n",
    "temperature": 15.910000000000025,
    "feels_like": 16.010000000000048,
    "temp_min": 15.910000000000025,
    "temp_max": 15.910000000000025,
    "pressure": 1018,
    "humidity": 94,
    "sea_level": 1018,
    "ground_level": 859,
    "visibility": 10000,
    "wind_speed": 1.35,
    "wind_degree": 157,
    "wind_gust": 1.42,
    "rain_1h": null,
    "clouds": 6,
    "datetime": "2024-11-02T14:03:23",
    "country": "IN",
    "sunrise": "2024-11-01T23:52:23",
    "sunset": "2024-11-02T11:01:42",
    "timezone": 19800,
    "city_id": 1266366,
    "city_name": "Kohima"
  },
  {
    "longitude": 85.8333,
    "latitude": 20.2333,
    "weather_id": 701,
    "weather_main": "Mist",
    "weather_description": "mist",
    "weather_icon": "50n",
    "temperature": 25.120000000000005,
    "feels_like": 25.99000000000001,
    "temp_min": 25.120000000000005,
    "temp_max": 25.120000000000005,
    "pressure": 1013,
    "humidity": 88,
    "sea_level": 1013,
    "ground_level": 1010,
    "visibility": 3500,
    "wind_speed": 0,
    "wind_degree": 0,
    "wind_gust": null,
    "rain_1h": null,
    "clouds": 20,
    "datetime": "2024-11-02T14:02:32",
    "country": "IN",
    "sunrise": "2024-11-02T00:18:52",
    "sunset": "2024-11-02T11:41:29",
    "timezone": 19800,
    "city_id": 1275817,
    "city_name": "Bhubaneswar"
  },
  {
    "longitude": 75.8167,
    "latitude": 26.9167,
    "weather_id": 721,
    "weather_main": "Haze",
    "weather_description": "haze",
    "weather_icon": "50n",
    "temperature": 26.620000000000005,
    "feels_like": 26.620000000000005,
    "temp_min": 26.620000000000005,
    "temp_max": 26.620000000000005,
    "pressure": 1013,
    "humidity": 41,
    "sea_level": 1013,
    "ground_level": 965,
    "visibility": 2500,
    "wind_speed": 0,
    "wind_degree": 0,
    "wind_gust": null,
    "rain_1h": null,
    "clouds": 0,
    "datetime": "2024-11-02T14:01:07",
    "country": "IN",
    "sunrise": "2024-11-02T01:07:14",
    "sunset": "2024-11-02T12:13:16",
    "timezone": 19800,
    "city_id": 1269515,
    "city_name": "Jaipur"
  },
  {
    "longitude": 88.6167,
    "latitude": 27.3333,
    "weather_id": 803,
    "weather_main": "Clouds",
    "weather_description": "broken clouds",
    "weather_icon": "04n",
    "temperature": 17.150000000000034,
    "feels_like": 17.430000000000007,
    "temp_min": 17.150000000000034,
    "temp_max": 17.150000000000034,
    "pressure": 1019,
    "humidity": 96,
    "sea_level": 1019,
    "ground_level": 821,
    "visibility": 10000,
    "wind_speed": 0.98,
    "wind_degree": 57,
    "wind_gust": 1.14,
    "rain_1h": null,
    "clouds": 64,
    "datetime": "2024-11-02T14:02:41",
    "country": "IN",
    "sunrise": "2024-11-02T00:16:33",
    "sunset": "2024-11-02T11:21:32",
    "timezone": 19800,
    "city_id": 1271631,
    "city_name": "Gangtok"
  },
  {
    "longitude": 80.2785,
    "latitude": 13.0878,
    "weather_id": 701,
    "weather_main": "Mist",
    "weather_description": "mist",
    "weather_icon": "50n",
    "temperature": 28.910000000000025,
    "feels_like": 34.920000000000016,
    "temp_min": 28.33000000000004,
    "temp_max": 29.470000000000027,
    "pressure": 1012,
    "humidity": 82,
    "sea_level": 1012,
    "ground_level": 1012,
    "visibility": 5000,
    "wind_speed": 3.09,
    "wind_degree": 100,
    "wind_gust": null,
    "rain_1h": null,
    "clouds": 40,
    "datetime": "2024-11-02T14:01:07",
    "country": "IN",
    "sunrise": "2024-11-02T00:32:58",
    "sunset": "2024-11-02T12:11:50",
    "timezone": 19800,
    "city_id": 1264527,
    "city_name": "Chennai"
  },
  {
    "longitude": 78.4744,
    "latitude": 17.3753,
    "weather_id": 721,
    "weather_main": "Haze",
    "weather_description": "haze",
    "weather_icon": "50n",
    "temperature": 26.230000000000018,
    "feels_like": 26.230000000000018,
    "temp_min": 25.730000000000018,
    "temp_max": 26.230000000000018,
    "pressure": 1014,
    "humidity": 69,
    "sea_level": 1014,
    "ground_level": 951,
    "visibility": 4000,
    "wind_speed": 2.57,
    "wind_degree": 100,
    "wind_gust": null,
    "rain_1h": null,
    "clouds": 40,
    "datetime": "2024-11-02T13:56:15",
    "country": "IN",
    "sunrise": "2024-11-02T00:44:59",
    "sunset": "2024-11-02T12:14:14",
    "timezone": 19800,
    "city_id": 1269843,
    "city_name": "Hyderabad"
  },
  {
    "longitude": 91.275,
    "latitude": 23.8364,
    "weather_id": 701,
    "weather_main": "Mist",
    "weather_description": "mist",
    "weather_icon": "50n",
    "temperature": 27.010000000000048,
    "feels_like": 30.660000000000025,
    "temp_min": 27.010000000000048,
    "temp_max": 27.010000000000048,
    "pressure": 1013,
    "humidity": 89,
    "sea_level": 1013,
    "ground_level": 1010,
    "visibility": 3500,
    "wind_speed": 1.54,
    "wind_degree": 30,
    "wind_gust": null,
    "rain_1h": null,
    "clouds": 0,
    "datetime": "2024-11-02T14:00:15",
    "country": "IN",
    "sunrise": "2024-11-02T00:01:27",
    "sunset": "2024-11-02T11:15:22",
    "timezone": 19800,
    "city_id": 1279290,
    "city_name": "Agartala"
  },
  {
    "longitude": 80.9167,
    "latitude": 26.85,
    "weather_id": 721,
    "weather_main": "Haze",
    "weather_description": "haze",
    "weather_icon": "50n",
    "temperature": 22.99000000000001,
    "feels_like": 23.120000000000005,
    "temp_min": 22.99000000000001,
    "temp_max": 22.99000000000001,
    "pressure": 1013,
    "humidity": 68,
    "sea_level": 1013,
    "ground_level": 999,
    "visibility": 5000,
    "wind_speed": 1.03,
    "wind_degree": 0,
    "wind_gust": null,
    "rain_1h": null,
    "clouds": 0,
    "datetime": "2024-11-02T13:54:51",
    "country": "IN",
    "sunrise": "2024-11-02T00:46:44",
    "sunset": "2024-11-02T11:52:57",
    "timezone": 19800,
    "city_id": 1264733,
    "city_name": "Lucknow"
  },
  {
    "longitude": 78.0437,
    "latitude": 30.3256,
    "weather_id": 800,
    "weather_main": "Clear",
    "weather_description": "clear sky",
    "weather_icon": "01n",
    "temperature": 21.189999999999998,
    "feels_like": 21.010000000000048,
    "temp_min": 21.189999999999998,
    "temp_max": 21.189999999999998,
    "pressure": 1016,
    "humidity": 63,
    "sea_level": 1016,
    "ground_level": 921,
    "visibility": 10000,
    "wind_speed": 2.4,
    "wind_degree": 45,
    "wind_gust": 1.96,
    "rain_1h": null,
    "clouds": 0,
    "datetime": "2024-11-02T14:01:08",
    "country": "IN",
    "sunrise": "2024-11-02T01:02:55",
    "sunset": "2024-11-02T11:59:46",
    "timezone": 19800,
    "city_id": 1273313,
    "city_name": "Dehradun"
  },
  {
    "longitude": 88.3697,
    "latitude": 22.5697,
    "weather_id": 721,
    "weather_main": "Haze",
    "weather_description": "haze",
    "weather_icon": "50n",
    "temperature": 29.970000000000027,
    "feels_like": 34.04000000000002,
    "temp_min": 29.970000000000027,
    "temp_max": 29.970000000000027,
    "pressure": 1013,
    "humidity": 66,
    "sea_level": 1013,
    "ground_level": 1012,
    "visibility": 3200,
    "wind_speed": 0,
    "wind_degree": 0,
    "wind_gust": null,
    "rain_1h": null,
    "clouds": 20,
    "datetime": "2024-11-02T14:02:26",
    "country": "IN",
    "sunrise": "2024-11-02T00:11:31",
    "sunset": "2024-11-02T11:28:33",
    "timezone": 19800,
    "city_id": 1275004,
    "city_name": "Kolkata"
  },
  {
    "longitude": 92.75,
    "latitude": 11.6667,
    "weather_id": 701,
    "weather_main": "Mist",
    "weather_description": "mist",
    "weather_icon": "50n",
    "temperature": 26.02000000000004,
    "feels_like": 26.02000000000004,
    "temp_min": 26.02000000000004,
    "temp_max": 26.02000000000004,
    "pressure": 1012,
    "humidity": 94,
    "sea_level": 1012,
    "ground_level": 1008,
    "visibility": 5000,
    "wind_speed": 1.03,
    "wind_degree": 0,
    "wind_gust": null,
    "rain_1h": null,
    "clouds": 40,
    "datetime": "2024-11-02T13:58:45",
    "country": "IN",
    "sunrise": "2024-11-01T23:41:31",
    "sunset": "2024-11-02T11:23:31",
    "timezone": 19800,
    "city_id": 1259385,
    "city_name": "Port Blair"
  },
  {
    "longitude": 76.7933,
    "latitude": 30.7343,
    "weather_id": 800,
    "weather_main": "Clear",
    "weather_description": "clear sky",
    "weather_icon": "01n",
    "temperature": 22.610000000000014,
    "feels_like": 21.660000000000025,
    "temp_min": 22.610000000000014,
    "temp_max": 22.610000000000014,
    "pressure": 1014,
    "humidity": 28,
    "sea_level": 1014,
    "ground_level": 973,
    "visibility": 10000,
    "wind_speed": 2.76,
    "wind_degree": 87,
    "wind_gust": 2.62,
    "rain_1h": null,
    "clouds": 0,
    "datetime": "2024-11-02T14:02:10",
    "country": "IN",
    "sunrise": "2024-11-02T01:08:29",
    "sunset": "2024-11-02T12:04:11",
    "timezone": 19800,
    "city_id": 1274746,
    "city_name": "Chandigarh"
  },
  {
    "longitude": 72.85,
    "latitude": 20.4167,
    "weather_id": 800,
    "weather_main": "Clear",
    "weather_description": "clear sky",
    "weather_icon": "01n",
    "temperature": 28.810000000000002,
    "feels_like": 31.32000000000005,
    "temp_min": 28.810000000000002,
    "temp_max": 28.810000000000002,
    "pressure": 1012,
    "humidity": 64,
    "sea_level": 1012,
    "ground_level": 1012,
    "visibility": 10000,
    "wind_speed": 4.11,
    "wind_degree": 349,
    "wind_gust": 5.18,
    "rain_1h": null,
    "clouds": 6,
    "datetime": "2024-11-02T14:00:56",
    "country": "IN",
    "sunrise": "2024-11-02T01:11:02",
    "sunset": "2024-11-02T12:33:11",
    "timezone": 19800,
    "city_id": 1273618,
    "city_name": "Daman"
  },
  {
    "longitude": 77.2311,
    "latitude": 28.6128,
    "weather_id": 721,
    "weather_main": "Haze",
    "weather_description": "haze",
    "weather_icon": "50n",
    "temperature": 28.090000000000032,
    "feels_like": 27.670000000000016,
    "temp_min": 28.090000000000032,
    "temp_max": 28.090000000000032,
    "pressure": 1013,
    "humidity": 39,
    "sea_level": 1013,
    "ground_level": 987,
    "visibility": 2500,
    "wind_speed": 2.06,
    "wind_degree": 20,
    "wind_gust": null,
    "rain_1h": null,
    "clouds": 0,
    "datetime": "2024-11-02T13:58:32",
    "country": "IN",
    "sunrise": "2024-11-02T01:03:49",
    "sunset": "2024-11-02T12:05:21",
    "timezone": 19800,
    "city_id": 1261481,
    "city_name": "New Delhi"
  },
  {
    "longitude": 72.642,
    "latitude": 10.5669,
    "weather_id": 804,
    "weather_main": "Clouds",
    "weather_description": "overcast clouds",
    "weather_icon": "04n",
    "temperature": 28.410000000000025,
    "feels_like": 32.28000000000003,
    "temp_min": 28.410000000000025,
    "temp_max": 28.410000000000025,
    "pressure": 1011,
    "humidity": 75,
    "sea_level": 1011,
    "ground_level": 1011,
    "visibility": 10000,
    "wind_speed": 3.62,
    "wind_degree": 325,
    "wind_gust": 3.8,
    "rain_1h": null,
    "clouds": 100,
    "datetime": "2024-11-02T14:03:29",
    "country": "IN",
    "sunrise": "2024-11-02T01:00:46",
    "sunset": "2024-11-02T12:45:08",
    "timezone": 19800,
    "city_id": 1267390,
    "city_name": "Kavaratti"
  },
  {
    "longitude": 79.8167,
    "latitude": 11.9333,
    "weather_id": 801,
    "weather_main": "Clouds",
    "weather_description": "few clouds",
    "weather_icon": "02n",
    "temperature": 27.560000000000002,
    "feels_like": 30.410000000000025,
    "temp_min": 27.560000000000002,
    "temp_max": 27.560000000000002,
    "pressure": 1012,
    "humidity": 75,
    "sea_level": 1012,
    "ground_level": 1011,
    "visibility": 10000,
    "wind_speed": 3.08,
    "wind_degree": 90,
    "wind_gust": 4.02,
    "rain_1h": null,
    "clouds": 17,
    "datetime": "2024-11-02T14:00:27",
    "country": "IN",
    "sunrise": "2024-11-02T00:33:33",
    "sunset": "2024-11-02T12:14:57",
    "timezone": 19800,
    "city_id": 1259424,
    "city_name": "Puducherry"
  }
]